tutorial/nand4_if.v
module nand4_if(a,y);
   input [3:0] a;
   output reg y;

   always @(a)
   begin
      if(a == 4'b1111)
      begin
         y=1'b0;
      end
      else
      begin
         y=1'b1;
      end
   end
endmodule

tutorial/tb_nand4.v
`timescale 1ns/1ps
module tb_nand4;
   reg [3:0] a;
   wire y;
   integer i;

   nand4_if tb(a,y);

   //------여기서 부터 아래 선까지는 waveform을 보기위한 파일을 만드는 코드이다.---- 
   initial
   begin
      $dumpfile("test_out.vcd");
      $dumpvars(-1,tb);  // tb는 위에 nand4_if tb(a,y)의 tb를 말한다. 
      $monitor("%b",y);
   end
   //------------------------------------------------------------------------------

   initial
   begin
      a=0;
      for(i=0; i<32; i = i+1)
      begin
         #20;
         a=i;
      end
      $finish;
   end
endmodule

tutorial/test_out.vcd
$date
	Wed Jul 26 16:07:50 2023
$end
$version
	Icarus Verilog
$end
$timescale
	1ps
$end
$scope module tb_nand4 $end
$scope module tb $end
$var wire 4 ! a [3:0] $end
$var reg 1 " y $end
$upscope $end
$upscope $end
$enddefinitions $end
$comment Show the parameter values. $end
$dumpall
$end
#0
$dumpvars
1"
b0 !
$end
#40000
b1 !
#60000
b10 !
#80000
b11 !
#100000
b100 !
#120000
b101 !
#140000
b110 !
#160000
b111 !
#180000
b1000 !
#200000
b1001 !
#220000
b1010 !
#240000
b1011 !
#260000
b1100 !
#280000
b1101 !
#300000
b1110 !
#320000
0"
b1111 !
#340000
1"
b0 !
#360000
b1 !
#380000
b10 !
#400000
b11 !
#420000
b100 !
#440000
b101 !
#460000
b110 !
#480000
b111 !
#500000
b1000 !
#520000
b1001 !
#540000
b1010 !
#560000
b1011 !
#580000
b1100 !
#600000
b1101 !
#620000
b1110 !
#640000
0"
b1111 !
